excel_convert_xml/TestCase_IHG_Adapter.xls
excel_convert_xml/__init__.py
excel_convert_xml/comm_xml.py
excel_convert_xml/config.ini
excel_convert_xml/excel.py
excel_to_xmind/__init__.py
excel_to_xmind/config.ini
excel_to_xmind/test_design.py
excel_to_xmind-1.0.0.dist-info/METADATA
excel_to_xmind-1.0.0.dist-info/WHEEL
excel_to_xmind-1.0.0.dist-info/top_level.txt
excel_to_xmind-1.0.0.dist-info/zip-safe
excel_to_xmind-1.0.0.dist-info/RECORD
