Metadata-Version: 2.1
Name: excel-to-xmind
Version: 1.0.0
Summary: excel testcase convert xmind file
Home-page: https://github.com
Author: jianzhong.zhou
Author-email: 1329870572@qq.com
License: MIT
Platform: UNKNOWN
Classifier: License :: OSI Approved :: MIT License
Classifier: Programming Language :: Python
Classifier: Intended Audience :: Developers
